tuna/__init__.py
tuna/first.py
tuna/second.py
tuna_test_vidit21srivastava-0.1.dist-info/LICENSE.txt
tuna_test_vidit21srivastava-0.1.dist-info/METADATA
tuna_test_vidit21srivastava-0.1.dist-info/WHEEL
tuna_test_vidit21srivastava-0.1.dist-info/top_level.txt
tuna_test_vidit21srivastava-0.1.dist-info/RECORD
