Metadata-Version: 2.1
Name: tuna-test-vidit21srivastava
Version: 0.1
Summary: this is description
Home-page: UNKNOWN
Author: Vidit Srivastava
Author-email: vidit21srivastava@gmai.com
License: UNKNOWN
Platform: UNKNOWN
Classifier: Programming Language :: Python :: 3
Classifier: License :: OSI Approved :: MIT License
Classifier: Operating System :: OS Independent
